motifcluster/__init__.py
motifcluster/clustering.py
motifcluster/indicators.py
motifcluster/motifadjacency.py
motifcluster/sampling.py
motifcluster/spectral.py
motifcluster/utils.py
motifcluster-0.2.3.dist-info/LICENSE
motifcluster-0.2.3.dist-info/METADATA
motifcluster-0.2.3.dist-info/WHEEL
motifcluster-0.2.3.dist-info/top_level.txt
motifcluster-0.2.3.dist-info/RECORD
