Metadata-Version: 2.1
Name: motifcluster
Version: 0.2.3
Summary: Motif-Based Spectral Clustering of Weighted Directed Networks
Home-page: https://github.com/WGUNDERWOOD/motifcluster
Author: William George Underwood, Andrew Elliott
Author-email: wgu2@princeton.edu
License: GPLv3
License-File: LICENSE
Requires-Dist: networkx (>=2.4)
Requires-Dist: numpy (>=1.18.3)
Requires-Dist: scipy (>=1.4.1)
Requires-Dist: scikit-learn (>=0.22.2)
